ada/__init__.py
ada/__main__.py
ada/py.typed
ada_cli-0.0.2.dist-info/entry_points.txt
ada_cli-0.0.2.dist-info/LICENSE
ada_cli-0.0.2.dist-info/WHEEL
ada_cli-0.0.2.dist-info/METADATA
ada_cli-0.0.2.dist-info/RECORD
