Metadata-Version: 2.1
Name: ada-cli
Version: 0.0.2
Summary: Ada CLI
Home-page: https://github.com/iamlucassantos/ada-cli
License: MIT
Author: Lucas Vieira dos Santos
Author-email: lucas6eng@gmail.com
Requires-Python: >=3.7,<4.0
Classifier: Development Status :: 2 - Pre-Alpha
Classifier: License :: OSI Approved :: MIT License
Classifier: Programming Language :: Python :: 3
Classifier: Programming Language :: Python :: 3.10
Classifier: Programming Language :: Python :: 3.7
Classifier: Programming Language :: Python :: 3.8
Classifier: Programming Language :: Python :: 3.9
Requires-Dist: click (>=8.0.1)
Requires-Dist: furo (==2022.4.7)
Project-URL: Changelog, https://github.com/iamlucassantos/ada-cli/releases
Project-URL: Documentation, https://ada-cli.readthedocs.io
Project-URL: Repository, https://github.com/iamlucassantos/ada-cli
